hairtest/__init__.py
hairtest/cli.py
hairtest/parser.py
hairtest/runner.py
hairtest/utils.py
hairtest-1.0.3.dist-info/licenses/LICENSE
hairtest-1.0.3.dist-info/METADATA
hairtest-1.0.3.dist-info/WHEEL
hairtest-1.0.3.dist-info/entry_points.txt
hairtest-1.0.3.dist-info/top_level.txt
hairtest-1.0.3.dist-info/RECORD
