Metadata-Version: 2.4
Name: hairtest
Version: 1.0.3
Summary: Airtest 并行测试工具
Home-page: https://github.com/yourusername/hairtest
Author: 王彦青
Author-email: your.email@example.com
Keywords: airtest automation testing parallel mobile
Classifier: Development Status :: 4 - Beta
Classifier: Intended Audience :: Developers
Classifier: License :: OSI Approved :: MIT License
Classifier: Operating System :: OS Independent
Classifier: Programming Language :: Python :: 3
Classifier: Programming Language :: Python :: 3.7
Classifier: Programming Language :: Python :: 3.8
Classifier: Programming Language :: Python :: 3.9
Classifier: Programming Language :: Python :: 3.10
Classifier: Programming Language :: Python :: 3.11
Requires-Python: >=3.7
License-File: LICENSE
Requires-Dist: airtest>=1.3.0
Requires-Dist: gevent
Requires-Dist: pyyaml
Requires-Dist: jinja2
Requires-Dist: requests
Dynamic: author
Dynamic: author-email
Dynamic: classifier
Dynamic: description
Dynamic: description-content-type
Dynamic: home-page
Dynamic: keywords
Dynamic: license-file
Dynamic: requires-dist
Dynamic: requires-python
Dynamic: summary
